django_css_inline/__init__.py
django_css_inline/apps.py
django_css_inline/exceptions.py
django_css_inline/templatetags/__init__.py
django_css_inline/templatetags/css_inline.py
django_css_inline/tests/__init__.py
django_css_inline-0.0.6.dist-info/LICENSE
django_css_inline-0.0.6.dist-info/METADATA
django_css_inline-0.0.6.dist-info/WHEEL
django_css_inline-0.0.6.dist-info/top_level.txt
django_css_inline-0.0.6.dist-info/RECORD
