Metadata-Version: 2.1
Name: django-css-inline
Version: 0.0.6
Summary: Django CSS Inline
Home-page: https://github.com/Aleksi44/django-css-inline
Author: Alexis Le Baron
Author-email: hello@snoweb.fr
License: GPL-3.0
Keywords: django css inline
Platform: linux
Classifier: Environment :: Web Environment
Classifier: Intended Audience :: Developers
Classifier: Programming Language :: Python
Classifier: Programming Language :: Python :: 3
Classifier: Programming Language :: Python :: 3.6
Classifier: Programming Language :: Python :: 3.7
Classifier: Programming Language :: Python :: 3.8
Classifier: Operating System :: OS Independent
Classifier: Topic :: Software Development
